README.rst
setup.py
hand_env/__init__.py
hand_env/config.py
hand_env.egg-info/PKG-INFO
hand_env.egg-info/SOURCES.txt
hand_env.egg-info/dependency_links.txt
hand_env.egg-info/top_level.txt