Metadata-Version: 1.0
Name: hand-env
Version: 1.0
Summary: global environment
Home-page: http://www.zsdx.cn
Author: newday_me
Author-email: newday_me@163.com
License: UNKNOWN
Platform: UNKNOWN
